[{"price": 780, "bidLots": 0, "bidFreq": 0, "bidBrokers": [], "offerLots": 1285, "offerFreq": 15, "offerBrokers": ["--"]}, {"price": 775, "bidLots": 0, "bidFreq": 0, "bidBrokers": [], "offerLots": 1019, "offerFreq": 4, "offerBrokers": ["--"]}, {"price": 770, "bidLots": 0, "bidFreq": 0, "bidBrokers": [], "offerLots": 14, "offerFreq": 2, "offerBrokers": ["--"]}, {"price": 765, "bidLots": 0, "bidFreq": 0, "bidBrokers": [], "offerLots": 10, "offerFreq": 2, "offerBrokers": ["--"]}, {"price": 760, "bidLots": 0, "bidFreq": 0, "bidBrokers": [], "offerLots": 417, "offerFreq": 5, "offerBrokers": ["--"]}, {"price": 755, "bidLots": 0, "bidFreq": 0, "bidBrokers": [], "offerLots": 55, "offerFreq": 2, "offerBrokers": ["--"]}, {"price": 750, "bidLots": 0, "bidFreq": 0, "bidBrokers": [], "offerLots": 42, "offerFreq": 3, "offerBrokers": ["--"]}, {"price": 745, "bidLots": 0, "bidFreq": 0, "bidBrokers": [], "offerLots": 122, "offerFreq": 4, "offerBrokers": ["--"]}, {"price": 740, "bidLots": 0, "bidFreq": 0, "bidBrokers": [], "offerLots": 31, "offerFreq": 4, "offerBrokers": ["--"]}, {"price": 735, "bidLots": 0, "bidFreq": 0, "bidBrokers": [], "offerLots": 698, "offerFreq": 3, "offerBrokers": ["--"]}, {"price": 730, "bidLots": 0, "bidFreq": 0, "bidBrokers": [], "offerLots": 14, "offerFreq": 3, "offerBrokers": ["--"]}, {"price": 725, "bidLots": 0, "bidFreq": 0, "bidBrokers": [], "offerLots": 138, "offerFreq": 7, "offerBrokers": ["--"]}, {"price": 720, "bidLots": 0, "bidFreq": 0, "bidBrokers": [], "offerLots": 90, "offerFreq": 8, "offerBrokers": ["--"]}, {"price": 715, "bidLots": 0, "bidFreq": 0, "bidBrokers": [], "offerLots": 175, "offerFreq": 5, "offerBrokers": ["--"]}, {"price": 710, "bidLots": 0, "bidFreq": 0, "bidBrokers": [], "offerLots": 286, "offerFreq": 7, "offerBrokers": ["--"]}, {"price": 705, "bidLots": 0, "bidFreq": 0, "bidBrokers": [], "offerLots": 937, "offerFreq": 6, "offerBrokers": ["--"]}, {"price": 700, "bidLots": 0, "bidFreq": 0, "bidBrokers": [], "offerLots": 1057, "offerFreq": 13, "offerBrokers": ["--"]}, {"price": 695, "bidLots": 0, "bidFreq": 0, "bidBrokers": [], "offerLots": 757, "offerFreq": 9, "offerBrokers": ["--"]}, {"price": 690, "bidLots": 0, "bidFreq": 0, "bidBrokers": [], "offerLots": 1535, "offerFreq": 5, "offerBrokers": ["--"]}, {"price": 685, "bidLots": 0, "bidFreq": 0, "bidBrokers": [], "offerLots": 984, "offerFreq": 7, "offerBrokers": ["--"]}, {"price": 680, "bidLots": 0, "bidFreq": 0, "bidBrokers": [], "offerLots": 2218, "offerFreq": 10, "offerBrokers": ["--"]}, {"price": 675, "bidLots": 0, "bidFreq": 0, "bidBrokers": [], "offerLots": 1874, "offerFreq": 6, "offerBrokers": ["--"]}, {"price": 670, "bidLots": 0, "bidFreq": 0, "bidBrokers": [], "offerLots": 1802, "offerFreq": 13, "offerBrokers": ["--"]}, {"price": 665, "bidLots": 0, "bidFreq": 0, "bidBrokers": [], "offerLots": 1575, "offerFreq": 10, "offerBrokers": ["--"]}, {"price": 660, "bidLots": 0, "bidFreq": 0, "bidBrokers": [], "offerLots": 1564, "offerFreq": 11, "offerBrokers": ["--"]}, {"price": 655, "bidLots": 0, "bidFreq": 0, "bidBrokers": [], "offerLots": 2768, "offerFreq": 10, "offerBrokers": ["--"]}, {"price": 650, "bidLots": 0, "bidFreq": 0, "bidBrokers": [], "offerLots": 8665, "offerFreq": 28, "offerBrokers": ["--"]}, {"price": 645, "bidLots": 0, "bidFreq": 0, "bidBrokers": [], "offerLots": 4387, "offerFreq": 24, "offerBrokers": ["--"]}, {"price": 640, "bidLots": 0, "bidFreq": 0, "bidBrokers": [], "offerLots": 6191, "offerFreq": 24, "offerBrokers": ["--"]}, {"price": 635, "bidLots": 0, "bidFreq": 0, "bidBrokers": [], "offerLots": 6043, "offerFreq": 52, "offerBrokers": ["--"]}, {"price": 630, "bidLots": 0, "bidFreq": 0, "bidBrokers": [], "offerLots": 1070, "offerFreq": 6, "offerBrokers": ["--"]}, {"price": 625, "bidLots": 3118, "bidFreq": 42, "bidBrokers": ["--"], "offerLots": 0, "offerFreq": 0, "offerBrokers": []}, {"price": 620, "bidLots": 6112, "bidFreq": 55, "bidBrokers": ["--"], "offerLots": 0, "offerFreq": 0, "offerBrokers": []}, {"price": 615, "bidLots": 4663, "bidFreq": 87, "bidBrokers": ["--"], "offerLots": 0, "offerFreq": 0, "offerBrokers": []}, {"price": 610, "bidLots": 19067, "bidFreq": 59, "bidBrokers": ["--"], "offerLots": 0, "offerFreq": 0, "offerBrokers": []}, {"price": 605, "bidLots": 2976, "bidFreq": 44, "bidBrokers": ["--"], "offerLots": 0, "offerFreq": 0, "offerBrokers": []}, {"price": 600, "bidLots": 12498, "bidFreq": 53, "bidBrokers": ["--"], "offerLots": 0, "offerFreq": 0, "offerBrokers": []}, {"price": 595, "bidLots": 668, "bidFreq": 20, "bidBrokers": ["--"], "offerLots": 0, "offerFreq": 0, "offerBrokers": []}, {"price": 590, "bidLots": 3856, "bidFreq": 17, "bidBrokers": ["--"], "offerLots": 0, "offerFreq": 0, "offerBrokers": []}, {"price": 585, "bidLots": 1232, "bidFreq": 13, "bidBrokers": ["--"], "offerLots": 0, "offerFreq": 0, "offerBrokers": []}, {"price": 580, "bidLots": 2137, "bidFreq": 11, "bidBrokers": ["--"], "offerLots": 0, "offerFreq": 0, "offerBrokers": []}, {"price": 575, "bidLots": 222, "bidFreq": 12, "bidBrokers": ["--"], "offerLots": 0, "offerFreq": 0, "offerBrokers": []}, {"price": 570, "bidLots": 416, "bidFreq": 13, "bidBrokers": ["--"], "offerLots": 0, "offerFreq": 0, "offerBrokers": []}, {"price": 565, "bidLots": 1106, "bidFreq": 8, "bidBrokers": ["--"], "offerLots": 0, "offerFreq": 0, "offerBrokers": []}, {"price": 560, "bidLots": 1486, "bidFreq": 14, "bidBrokers": ["--"], "offerLots": 0, "offerFreq": 0, "offerBrokers": []}, {"price": 555, "bidLots": 1070, "bidFreq": 9, "bidBrokers": ["--"], "offerLots": 0, "offerFreq": 0, "offerBrokers": []}, {"price": 550, "bidLots": 7419, "bidFreq": 20, "bidBrokers": ["--"], "offerLots": 0, "offerFreq": 0, "offerBrokers": []}, {"price": 545, "bidLots": 154, "bidFreq": 5, "bidBrokers": ["--"], "offerLots": 0, "offerFreq": 0, "offerBrokers": []}, {"price": 540, "bidLots": 1033, "bidFreq": 8, "bidBrokers": ["--"], "offerLots": 0, "offerFreq": 0, "offerBrokers": []}, {"price": 535, "bidLots": 3157, "bidFreq": 13, "bidBrokers": ["--"], "offerLots": 0, "offerFreq": 0, "offerBrokers": []}]