[{"price": 9000, "bidLots": 0, "bidFreq": 0, "bidBrokers": [], "offerLots": 2, "offerFreq": 1, "offerBrokers": ["YP"]}, {"price": 5075, "bidLots": 0, "bidFreq": 0, "bidBrokers": [], "offerLots": 2062, "offerFreq": 59, "offerBrokers": []}, {"price": 5050, "bidLots": 0, "bidFreq": 0, "bidBrokers": [], "offerLots": 807, "offerFreq": 29, "offerBrokers": []}, {"price": 5025, "bidLots": 0, "bidFreq": 0, "bidBrokers": [], "offerLots": 772, "offerFreq": 14, "offerBrokers": []}, {"price": 5000, "bidLots": 0, "bidFreq": 0, "bidBrokers": [], "offerLots": 3017, "offerFreq": 102, "offerBrokers": []}, {"price": 4990, "bidLots": 0, "bidFreq": 0, "bidBrokers": [], "offerLots": 48, "offerFreq": 7, "offerBrokers": []}, {"price": 4980, "bidLots": 0, "bidFreq": 0, "bidBrokers": [], "offerLots": 216, "offerFreq": 7, "offerBrokers": []}, {"price": 4970, "bidLots": 0, "bidFreq": 0, "bidBrokers": [], "offerLots": 17, "offerFreq": 3, "offerBrokers": []}, {"price": 4960, "bidLots": 0, "bidFreq": 0, "bidBrokers": [], "offerLots": 121, "offerFreq": 9, "offerBrokers": []}, {"price": 4950, "bidLots": 0, "bidFreq": 0, "bidBrokers": [], "offerLots": 812, "offerFreq": 13, "offerBrokers": []}, {"price": 4940, "bidLots": 0, "bidFreq": 0, "bidBrokers": [], "offerLots": 10, "offerFreq": 3, "offerBrokers": []}, {"price": 4930, "bidLots": 0, "bidFreq": 0, "bidBrokers": [], "offerLots": 69, "offerFreq": 5, "offerBrokers": []}, {"price": 4920, "bidLots": 0, "bidFreq": 0, "bidBrokers": [], "offerLots": 28, "offerFreq": 6, "offerBrokers": []}, {"price": 4910, "bidLots": 0, "bidFreq": 0, "bidBrokers": [], "offerLots": 27, "offerFreq": 3, "offerBrokers": []}, {"price": 4900, "bidLots": 0, "bidFreq": 0, "bidBrokers": [], "offerLots": 2627, "offerFreq": 28, "offerBrokers": []}, {"price": 4890, "bidLots": 0, "bidFreq": 0, "bidBrokers": [], "offerLots": 58, "offerFreq": 6, "offerBrokers": []}, {"price": 4880, "bidLots": 0, "bidFreq": 0, "bidBrokers": [], "offerLots": 221, "offerFreq": 4, "offerBrokers": []}, {"price": 4870, "bidLots": 0, "bidFreq": 0, "bidBrokers": [], "offerLots": 143, "offerFreq": 4, "offerBrokers": []}, {"price": 4860, "bidLots": 0, "bidFreq": 0, "bidBrokers": [], "offerLots": 34, "offerFreq": 5, "offerBrokers": []}, {"price": 4850, "bidLots": 0, "bidFreq": 0, "bidBrokers": [], "offerLots": 2384, "offerFreq": 14, "offerBrokers": []}, {"price": 4840, "bidLots": 0, "bidFreq": 0, "bidBrokers": [], "offerLots": 106, "offerFreq": 3, "offerBrokers": []}, {"price": 4830, "bidLots": 0, "bidFreq": 0, "bidBrokers": [], "offerLots": 30, "offerFreq": 4, "offerBrokers": []}, {"price": 4820, "bidLots": 0, "bidFreq": 0, "bidBrokers": [], "offerLots": 14, "offerFreq": 6, "offerBrokers": []}, {"price": 4810, "bidLots": 0, "bidFreq": 0, "bidBrokers": [], "offerLots": 618, "offerFreq": 4, "offerBrokers": []}, {"price": 4800, "bidLots": 0, "bidFreq": 0, "bidBrokers": [], "offerLots": 2256, "offerFreq": 52, "offerBrokers": []}, {"price": 4790, "bidLots": 0, "bidFreq": 0, "bidBrokers": [], "offerLots": 277, "offerFreq": 9, "offerBrokers": []}, {"price": 4780, "bidLots": 0, "bidFreq": 0, "bidBrokers": [], "offerLots": 137, "offerFreq": 6, "offerBrokers": []}, {"price": 4770, "bidLots": 0, "bidFreq": 0, "bidBrokers": [], "offerLots": 20, "offerFreq": 4, "offerBrokers": []}, {"price": 4760, "bidLots": 0, "bidFreq": 0, "bidBrokers": [], "offerLots": 24, "offerFreq": 4, "offerBrokers": []}, {"price": 4750, "bidLots": 0, "bidFreq": 0, "bidBrokers": [], "offerLots": 232, "offerFreq": 19, "offerBrokers": []}, {"price": 4740, "bidLots": 0, "bidFreq": 0, "bidBrokers": [], "offerLots": 26, "offerFreq": 3, "offerBrokers": []}, {"price": 4730, "bidLots": 0, "bidFreq": 0, "bidBrokers": [], "offerLots": 373, "offerFreq": 5, "offerBrokers": []}, {"price": 4720, "bidLots": 0, "bidFreq": 0, "bidBrokers": [], "offerLots": 143, "offerFreq": 4, "offerBrokers": []}, {"price": 4710, "bidLots": 0, "bidFreq": 0, "bidBrokers": [], "offerLots": 83, "offerFreq": 5, "offerBrokers": []}, {"price": 4700, "bidLots": 0, "bidFreq": 0, "bidBrokers": [], "offerLots": 1442, "offerFreq": 36, "offerBrokers": []}, {"price": 4690, "bidLots": 0, "bidFreq": 0, "bidBrokers": [], "offerLots": 91, "offerFreq": 7, "offerBrokers": []}, {"price": 4680, "bidLots": 0, "bidFreq": 0, "bidBrokers": [], "offerLots": 96, "offerFreq": 7, "offerBrokers": []}, {"price": 4670, "bidLots": 0, "bidFreq": 0, "bidBrokers": [], "offerLots": 9, "offerFreq": 5, "offerBrokers": []}, {"price": 4660, "bidLots": 0, "bidFreq": 0, "bidBrokers": [], "offerLots": 6, "offerFreq": 2, "offerBrokers": []}, {"price": 4650, "bidLots": 0, "bidFreq": 0, "bidBrokers": [], "offerLots": 815, "offerFreq": 14, "offerBrokers": []}, {"price": 4640, "bidLots": 0, "bidFreq": 0, "bidBrokers": [], "offerLots": 99, "offerFreq": 5, "offerBrokers": []}, {"price": 4630, "bidLots": 0, "bidFreq": 0, "bidBrokers": [], "offerLots": 91, "offerFreq": 3, "offerBrokers": []}, {"price": 4620, "bidLots": 0, "bidFreq": 0, "bidBrokers": [], "offerLots": 80, "offerFreq": 7, "offerBrokers": []}, {"price": 4610, "bidLots": 0, "bidFreq": 0, "bidBrokers": [], "offerLots": 11, "offerFreq": 4, "offerBrokers": []}, {"price": 4600, "bidLots": 0, "bidFreq": 0, "bidBrokers": [], "offerLots": 2152, "offerFreq": 41, "offerBrokers": []}, {"price": 4590, "bidLots": 0, "bidFreq": 0, "bidBrokers": [], "offerLots": 97, "offerFreq": 7, "offerBrokers": []}, {"price": 4580, "bidLots": 0, "bidFreq": 0, "bidBrokers": [], "offerLots": 5, "offerFreq": 5, "offerBrokers": []}, {"price": 4570, "bidLots": 0, "bidFreq": 0, "bidBrokers": [], "offerLots": 12, "offerFreq": 4, "offerBrokers": []}, {"price": 4560, "bidLots": 0, "bidFreq": 0, "bidBrokers": [], "offerLots": 37, "offerFreq": 6, "offerBrokers": []}, {"price": 4550, "bidLots": 0, "bidFreq": 0, "bidBrokers": [], "offerLots": 509, "offerFreq": 16, "offerBrokers": []}, {"price": 4540, "bidLots": 0, "bidFreq": 0, "bidBrokers": [], "offerLots": 148, "offerFreq": 6, "offerBrokers": []}, {"price": 4530, "bidLots": 0, "bidFreq": 0, "bidBrokers": [], "offerLots": 43, "offerFreq": 3, "offerBrokers": []}, {"price": 4520, "bidLots": 0, "bidFreq": 0, "bidBrokers": [], "offerLots": 188, "offerFreq": 11, "offerBrokers": []}, {"price": 4510, "bidLots": 0, "bidFreq": 0, "bidBrokers": [], "offerLots": 583, "offerFreq": 5, "offerBrokers": []}, {"price": 4500, "bidLots": 0, "bidFreq": 0, "bidBrokers": [], "offerLots": 3433, "offerFreq": 114, "offerBrokers": []}, {"price": 4490, "bidLots": 0, "bidFreq": 0, "bidBrokers": [], "offerLots": 284, "offerFreq": 16, "offerBrokers": []}, {"price": 4480, "bidLots": 0, "bidFreq": 0, "bidBrokers": [], "offerLots": 820, "offerFreq": 12, "offerBrokers": []}, {"price": 4470, "bidLots": 0, "bidFreq": 0, "bidBrokers": [], "offerLots": 152, "offerFreq": 10, "offerBrokers": []}, {"price": 4460, "bidLots": 0, "bidFreq": 0, "bidBrokers": [], "offerLots": 50, "offerFreq": 5, "offerBrokers": []}, {"price": 4450, "bidLots": 0, "bidFreq": 0, "bidBrokers": [], "offerLots": 1608, "offerFreq": 43, "offerBrokers": []}, {"price": 4440, "bidLots": 0, "bidFreq": 0, "bidBrokers": [], "offerLots": 340, "offerFreq": 13, "offerBrokers": []}, {"price": 4430, "bidLots": 0, "bidFreq": 0, "bidBrokers": [], "offerLots": 63, "offerFreq": 4, "offerBrokers": []}, {"price": 4420, "bidLots": 0, "bidFreq": 0, "bidBrokers": [], "offerLots": 653, "offerFreq": 6, "offerBrokers": []}, {"price": 4410, "bidLots": 0, "bidFreq": 0, "bidBrokers": [], "offerLots": 262, "offerFreq": 7, "offerBrokers": []}, {"price": 4400, "bidLots": 0, "bidFreq": 0, "bidBrokers": [], "offerLots": 2503, "offerFreq": 66, "offerBrokers": []}, {"price": 4390, "bidLots": 0, "bidFreq": 0, "bidBrokers": [], "offerLots": 88, "offerFreq": 8, "offerBrokers": []}, {"price": 4380, "bidLots": 0, "bidFreq": 0, "bidBrokers": [], "offerLots": 691, "offerFreq": 12, "offerBrokers": []}, {"price": 4370, "bidLots": 0, "bidFreq": 0, "bidBrokers": [], "offerLots": 160, "offerFreq": 7, "offerBrokers": []}, {"price": 4360, "bidLots": 0, "bidFreq": 0, "bidBrokers": [], "offerLots": 210, "offerFreq": 9, "offerBrokers": []}, {"price": 4350, "bidLots": 0, "bidFreq": 0, "bidBrokers": [], "offerLots": 3204, "offerFreq": 39, "offerBrokers": []}, {"price": 4340, "bidLots": 0, "bidFreq": 0, "bidBrokers": [], "offerLots": 223, "offerFreq": 17, "offerBrokers": []}, {"price": 4330, "bidLots": 0, "bidFreq": 0, "bidBrokers": [], "offerLots": 468, "offerFreq": 9, "offerBrokers": []}, {"price": 4320, "bidLots": 0, "bidFreq": 0, "bidBrokers": [], "offerLots": 1354, "offerFreq": 16, "offerBrokers": []}, {"price": 4310, "bidLots": 0, "bidFreq": 0, "bidBrokers": [], "offerLots": 117, "offerFreq": 10, "offerBrokers": []}, {"price": 4300, "bidLots": 0, "bidFreq": 0, "bidBrokers": [], "offerLots": 6244, "offerFreq": 117, "offerBrokers": []}, {"price": 4290, "bidLots": 0, "bidFreq": 0, "bidBrokers": [], "offerLots": 3129, "offerFreq": 31, "offerBrokers": []}, {"price": 4280, "bidLots": 0, "bidFreq": 0, "bidBrokers": [], "offerLots": 1323, "offerFreq": 22, "offerBrokers": []}, {"price": 4270, "bidLots": 0, "bidFreq": 0, "bidBrokers": [], "offerLots": 604, "offerFreq": 20, "offerBrokers": []}, {"price": 4260, "bidLots": 0, "bidFreq": 0, "bidBrokers": [], "offerLots": 3672, "offerFreq": 16, "offerBrokers": []}, {"price": 4250, "bidLots": 0, "bidFreq": 0, "bidBrokers": [], "offerLots": 2161, "offerFreq": 89, "offerBrokers": []}, {"price": 4240, "bidLots": 0, "bidFreq": 0, "bidBrokers": [], "offerLots": 1139, "offerFreq": 31, "offerBrokers": []}, {"price": 4230, "bidLots": 0, "bidFreq": 0, "bidBrokers": [], "offerLots": 1994, "offerFreq": 31, "offerBrokers": []}, {"price": 4220, "bidLots": 0, "bidFreq": 0, "bidBrokers": [], "offerLots": 2496, "offerFreq": 49, "offerBrokers": []}, {"price": 4210, "bidLots": 0, "bidFreq": 0, "bidBrokers": [], "offerLots": 1940, "offerFreq": 47, "offerBrokers": []}, {"price": 4200, "bidLots": 0, "bidFreq": 0, "bidBrokers": [], "offerLots": 21020, "offerFreq": 266, "offerBrokers": []}, {"price": 4190, "bidLots": 0, "bidFreq": 0, "bidBrokers": [], "offerLots": 3875, "offerFreq": 119, "offerBrokers": []}, {"price": 4180, "bidLots": 0, "bidFreq": 0, "bidBrokers": [], "offerLots": 6146, "offerFreq": 83, "offerBrokers": []}, {"price": 4170, "bidLots": 0, "bidFreq": 0, "bidBrokers": [], "offerLots": 4301, "offerFreq": 92, "offerBrokers": []}, {"price": 4160, "bidLots": 0, "bidFreq": 0, "bidBrokers": [], "offerLots": 4040, "offerFreq": 83, "offerBrokers": []}, {"price": 4150, "bidLots": 0, "bidFreq": 0, "bidBrokers": [], "offerLots": 13648, "offerFreq": 259, "offerBrokers": []}, {"price": 4140, "bidLots": 0, "bidFreq": 0, "bidBrokers": [], "offerLots": 5904, "offerFreq": 179, "offerBrokers": []}, {"price": 4130, "bidLots": 0, "bidFreq": 0, "bidBrokers": [], "offerLots": 595, "offerFreq": 8, "offerBrokers": []}, {"price": 4120, "bidLots": 0, "bidFreq": 0, "bidBrokers": [], "offerLots": 673, "offerFreq": 5, "offerBrokers": []}, {"price": 4110, "bidLots": 3227, "bidFreq": 44, "bidBrokers": [], "offerLots": 0, "offerFreq": 0, "offerBrokers": []}, {"price": 4100, "bidLots": 2777, "bidFreq": 92, "bidBrokers": [], "offerLots": 0, "offerFreq": 0, "offerBrokers": []}, {"price": 4090, "bidLots": 2638, "bidFreq": 84, "bidBrokers": [], "offerLots": 0, "offerFreq": 0, "offerBrokers": []}, {"price": 4080, "bidLots": 5389, "bidFreq": 213, "bidBrokers": [], "offerLots": 0, "offerFreq": 0, "offerBrokers": []}, {"price": 4070, "bidLots": 8719, "bidFreq": 265, "bidBrokers": [], "offerLots": 0, "offerFreq": 0, "offerBrokers": []}, {"price": 4060, "bidLots": 3116, "bidFreq": 76, "bidBrokers": [], "offerLots": 0, "offerFreq": 0, "offerBrokers": []}, {"price": 4050, "bidLots": 3539, "bidFreq": 137, "bidBrokers": [], "offerLots": 0, "offerFreq": 0, "offerBrokers": []}, {"price": 4040, "bidLots": 1942, "bidFreq": 43, "bidBrokers": [], "offerLots": 0, "offerFreq": 0, "offerBrokers": []}, {"price": 4030, "bidLots": 2529, "bidFreq": 41, "bidBrokers": [], "offerLots": 0, "offerFreq": 0, "offerBrokers": []}, {"price": 4020, "bidLots": 1090, "bidFreq": 43, "bidBrokers": [], "offerLots": 0, "offerFreq": 0, "offerBrokers": []}, {"price": 4010, "bidLots": 1668, "bidFreq": 51, "bidBrokers": [], "offerLots": 0, "offerFreq": 0, "offerBrokers": []}, {"price": 4000, "bidLots": 6289, "bidFreq": 189, "bidBrokers": [], "offerLots": 0, "offerFreq": 0, "offerBrokers": []}, {"price": 3990, "bidLots": 2252, "bidFreq": 44, "bidBrokers": [], "offerLots": 0, "offerFreq": 0, "offerBrokers": []}, {"price": 3980, "bidLots": 540, "bidFreq": 44, "bidBrokers": [], "offerLots": 0, "offerFreq": 0, "offerBrokers": []}, {"price": 3970, "bidLots": 463, "bidFreq": 26, "bidBrokers": [], "offerLots": 0, "offerFreq": 0, "offerBrokers": []}, {"price": 3960, "bidLots": 509, "bidFreq": 25, "bidBrokers": [], "offerLots": 0, "offerFreq": 0, "offerBrokers": []}, {"price": 3950, "bidLots": 747, "bidFreq": 42, "bidBrokers": [], "offerLots": 0, "offerFreq": 0, "offerBrokers": []}, {"price": 3940, "bidLots": 436, "bidFreq": 20, "bidBrokers": [], "offerLots": 0, "offerFreq": 0, "offerBrokers": []}, {"price": 3930, "bidLots": 136, "bidFreq": 10, "bidBrokers": [], "offerLots": 0, "offerFreq": 0, "offerBrokers": []}, {"price": 3920, "bidLots": 249, "bidFreq": 15, "bidBrokers": [], "offerLots": 0, "offerFreq": 0, "offerBrokers": []}, {"price": 3910, "bidLots": 167, "bidFreq": 12, "bidBrokers": [], "offerLots": 0, "offerFreq": 0, "offerBrokers": []}, {"price": 3900, "bidLots": 871, "bidFreq": 72, "bidBrokers": [], "offerLots": 0, "offerFreq": 0, "offerBrokers": []}, {"price": 3890, "bidLots": 143, "bidFreq": 9, "bidBrokers": [], "offerLots": 0, "offerFreq": 0, "offerBrokers": []}, {"price": 3880, "bidLots": 738, "bidFreq": 15, "bidBrokers": [], "offerLots": 0, "offerFreq": 0, "offerBrokers": []}, {"price": 3870, "bidLots": 203, "bidFreq": 11, "bidBrokers": [], "offerLots": 0, "offerFreq": 0, "offerBrokers": []}, {"price": 3860, "bidLots": 574, "bidFreq": 22, "bidBrokers": [], "offerLots": 0, "offerFreq": 0, "offerBrokers": []}, {"price": 3850, "bidLots": 1753, "bidFreq": 34, "bidBrokers": [], "offerLots": 0, "offerFreq": 0, "offerBrokers": []}, {"price": 3840, "bidLots": 117, "bidFreq": 15, "bidBrokers": [], "offerLots": 0, "offerFreq": 0, "offerBrokers": []}, {"price": 3830, "bidLots": 319, "bidFreq": 7, "bidBrokers": [], "offerLots": 0, "offerFreq": 0, "offerBrokers": []}, {"price": 3820, "bidLots": 2, "bidFreq": 1, "bidBrokers": [], "offerLots": 0, "offerFreq": 0, "offerBrokers": []}, {"price": 3810, "bidLots": 79, "bidFreq": 11, "bidBrokers": [], "offerLots": 0, "offerFreq": 0, "offerBrokers": []}, {"price": 3800, "bidLots": 344, "bidFreq": 40, "bidBrokers": [], "offerLots": 0, "offerFreq": 0, "offerBrokers": []}, {"price": 3790, "bidLots": 2, "bidFreq": 2, "bidBrokers": [], "offerLots": 0, "offerFreq": 0, "offerBrokers": []}, {"price": 3780, "bidLots": 18, "bidFreq": 3, "bidBrokers": [], "offerLots": 0, "offerFreq": 0, "offerBrokers": []}, {"price": 3770, "bidLots": 13, "bidFreq": 2, "bidBrokers": [], "offerLots": 0, "offerFreq": 0, "offerBrokers": []}, {"price": 3760, "bidLots": 10, "bidFreq": 4, "bidBrokers": [], "offerLots": 0, "offerFreq": 0, "offerBrokers": []}, {"price": 3750, "bidLots": 1089, "bidFreq": 13, "bidBrokers": [], "offerLots": 0, "offerFreq": 0, "offerBrokers": []}, {"price": 3740, "bidLots": 56, "bidFreq": 3, "bidBrokers": [], "offerLots": 0, "offerFreq": 0, "offerBrokers": []}, {"price": 3730, "bidLots": 11, "bidFreq": 4, "bidBrokers": [], "offerLots": 0, "offerFreq": 0, "offerBrokers": []}, {"price": 3720, "bidLots": 3, "bidFreq": 2, "bidBrokers": [], "offerLots": 0, "offerFreq": 0, "offerBrokers": []}, {"price": 3710, "bidLots": 24, "bidFreq": 3, "bidBrokers": [], "offerLots": 0, "offerFreq": 0, "offerBrokers": []}, {"price": 3700, "bidLots": 1163, "bidFreq": 22, "bidBrokers": [], "offerLots": 0, "offerFreq": 0, "offerBrokers": []}, {"price": 3690, "bidLots": 9, "bidFreq": 4, "bidBrokers": [], "offerLots": 0, "offerFreq": 0, "offerBrokers": []}, {"price": 3680, "bidLots": 228, "bidFreq": 5, "bidBrokers": [], "offerLots": 0, "offerFreq": 0, "offerBrokers": []}, {"price": 3670, "bidLots": 9, "bidFreq": 1, "bidBrokers": [], "offerLots": 0, "offerFreq": 0, "offerBrokers": []}, {"price": 3660, "bidLots": 27, "bidFreq": 3, "bidBrokers": [], "offerLots": 0, "offerFreq": 0, "offerBrokers": []}, {"price": 3650, "bidLots": 101, "bidFreq": 11, "bidBrokers": [], "offerLots": 0, "offerFreq": 0, "offerBrokers": []}, {"price": 3640, "bidLots": 55, "bidFreq": 1, "bidBrokers": [], "offerLots": 0, "offerFreq": 0, "offerBrokers": []}, {"price": 3630, "bidLots": 8, "bidFreq": 2, "bidBrokers": [], "offerLots": 0, "offerFreq": 0, "offerBrokers": []}, {"price": 3620, "bidLots": 673, "bidFreq": 2, "bidBrokers": [], "offerLots": 0, "offerFreq": 0, "offerBrokers": []}, {"price": 3610, "bidLots": 56, "bidFreq": 3, "bidBrokers": [], "offerLots": 0, "offerFreq": 0, "offerBrokers": []}, {"price": 3600, "bidLots": 1146, "bidFreq": 25, "bidBrokers": [], "offerLots": 0, "offerFreq": 0, "offerBrokers": []}, {"price": 3580, "bidLots": 71, "bidFreq": 3, "bidBrokers": [], "offerLots": 0, "offerFreq": 0, "offerBrokers": []}, {"price": 3570, "bidLots": 5, "bidFreq": 2, "bidBrokers": [], "offerLots": 0, "offerFreq": 0, "offerBrokers": []}, {"price": 3560, "bidLots": 29, "bidFreq": 14, "bidBrokers": [], "offerLots": 0, "offerFreq": 0, "offerBrokers": []}, {"price": 3550, "bidLots": 936, "bidFreq": 10, "bidBrokers": [], "offerLots": 0, "offerFreq": 0, "offerBrokers": []}, {"price": 3540, "bidLots": 2, "bidFreq": 2, "bidBrokers": [], "offerLots": 0, "offerFreq": 0, "offerBrokers": []}, {"price": 3530, "bidLots": 2, "bidFreq": 2, "bidBrokers": [], "offerLots": 0, "offerFreq": 0, "offerBrokers": []}, {"price": 3520, "bidLots": 103, "bidFreq": 4, "bidBrokers": [], "offerLots": 0, "offerFreq": 0, "offerBrokers": []}, {"price": 3510, "bidLots": 61, "bidFreq": 6, "bidBrokers": [], "offerLots": 0, "offerFreq": 0, "offerBrokers": []}, {"price": 3500, "bidLots": 767, "bidFreq": 54, "bidBrokers": [], "offerLots": 0, "offerFreq": 0, "offerBrokers": []}, {"price": 3490, "bidLots": 9, "bidFreq": 2, "bidBrokers": [], "offerLots": 0, "offerFreq": 0, "offerBrokers": []}, {"price": 3480, "bidLots": 225, "bidFreq": 7, "bidBrokers": [], "offerLots": 0, "offerFreq": 0, "offerBrokers": []}, {"price": 3470, "bidLots": 45, "bidFreq": 9, "bidBrokers": [], "offerLots": 0, "offerFreq": 0, "offerBrokers": []}, {"price": 3460, "bidLots": 572, "bidFreq": 27, "bidBrokers": [], "offerLots": 0, "offerFreq": 0, "offerBrokers": []}]