[{"price": 1965, "bidLots": 0, "bidFreq": 0, "bidBrokers": [], "offerLots": 299, "offerFreq": 12, "offerBrokers": ["--"]}, {"price": 1960, "bidLots": 0, "bidFreq": 0, "bidBrokers": [], "offerLots": 18, "offerFreq": 2, "offerBrokers": ["--"]}, {"price": 1955, "bidLots": 0, "bidFreq": 0, "bidBrokers": [], "offerLots": 1, "offerFreq": 1, "offerBrokers": ["--"]}, {"price": 1950, "bidLots": 0, "bidFreq": 0, "bidBrokers": [], "offerLots": 47, "offerFreq": 7, "offerBrokers": ["--"]}, {"price": 1940, "bidLots": 0, "bidFreq": 0, "bidBrokers": [], "offerLots": 1, "offerFreq": 1, "offerBrokers": ["--"]}, {"price": 1935, "bidLots": 0, "bidFreq": 0, "bidBrokers": [], "offerLots": 1, "offerFreq": 1, "offerBrokers": ["--"]}, {"price": 1930, "bidLots": 0, "bidFreq": 0, "bidBrokers": [], "offerLots": 158, "offerFreq": 2, "offerBrokers": ["--"]}, {"price": 1920, "bidLots": 0, "bidFreq": 0, "bidBrokers": [], "offerLots": 39, "offerFreq": 3, "offerBrokers": ["--"]}, {"price": 1910, "bidLots": 0, "bidFreq": 0, "bidBrokers": [], "offerLots": 3, "offerFreq": 1, "offerBrokers": ["--"]}, {"price": 1905, "bidLots": 0, "bidFreq": 0, "bidBrokers": [], "offerLots": 18, "offerFreq": 2, "offerBrokers": ["--"]}, {"price": 1900, "bidLots": 0, "bidFreq": 0, "bidBrokers": [], "offerLots": 203, "offerFreq": 12, "offerBrokers": ["--"]}, {"price": 1895, "bidLots": 0, "bidFreq": 0, "bidBrokers": [], "offerLots": 601, "offerFreq": 2, "offerBrokers": ["--"]}, {"price": 1890, "bidLots": 0, "bidFreq": 0, "bidBrokers": [], "offerLots": 408, "offerFreq": 4, "offerBrokers": ["--"]}, {"price": 1885, "bidLots": 0, "bidFreq": 0, "bidBrokers": [], "offerLots": 2, "offerFreq": 2, "offerBrokers": ["--"]}, {"price": 1880, "bidLots": 0, "bidFreq": 0, "bidBrokers": [], "offerLots": 8, "offerFreq": 2, "offerBrokers": ["--"]}, {"price": 1870, "bidLots": 0, "bidFreq": 0, "bidBrokers": [], "offerLots": 6, "offerFreq": 2, "offerBrokers": ["--"]}, {"price": 1865, "bidLots": 0, "bidFreq": 0, "bidBrokers": [], "offerLots": 800, "offerFreq": 1, "offerBrokers": ["--"]}, {"price": 1855, "bidLots": 0, "bidFreq": 0, "bidBrokers": [], "offerLots": 21, "offerFreq": 1, "offerBrokers": ["--"]}, {"price": 1850, "bidLots": 0, "bidFreq": 0, "bidBrokers": [], "offerLots": 96, "offerFreq": 8, "offerBrokers": ["--"]}, {"price": 1845, "bidLots": 0, "bidFreq": 0, "bidBrokers": [], "offerLots": 5, "offerFreq": 1, "offerBrokers": ["--"]}, {"price": 1840, "bidLots": 0, "bidFreq": 0, "bidBrokers": [], "offerLots": 1, "offerFreq": 1, "offerBrokers": ["--"]}, {"price": 1835, "bidLots": 0, "bidFreq": 0, "bidBrokers": [], "offerLots": 145, "offerFreq": 1, "offerBrokers": ["--"]}, {"price": 1830, "bidLots": 0, "bidFreq": 0, "bidBrokers": [], "offerLots": 135, "offerFreq": 1, "offerBrokers": ["--"]}, {"price": 1825, "bidLots": 0, "bidFreq": 0, "bidBrokers": [], "offerLots": 2, "offerFreq": 2, "offerBrokers": ["--"]}, {"price": 1820, "bidLots": 0, "bidFreq": 0, "bidBrokers": [], "offerLots": 1, "offerFreq": 1, "offerBrokers": ["--"]}, {"price": 1815, "bidLots": 0, "bidFreq": 0, "bidBrokers": [], "offerLots": 60, "offerFreq": 1, "offerBrokers": ["--"]}, {"price": 1810, "bidLots": 0, "bidFreq": 0, "bidBrokers": [], "offerLots": 1, "offerFreq": 1, "offerBrokers": ["--"]}, {"price": 1805, "bidLots": 0, "bidFreq": 0, "bidBrokers": [], "offerLots": 18, "offerFreq": 2, "offerBrokers": ["--"]}, {"price": 1800, "bidLots": 0, "bidFreq": 0, "bidBrokers": [], "offerLots": 306, "offerFreq": 11, "offerBrokers": ["--"]}, {"price": 1795, "bidLots": 0, "bidFreq": 0, "bidBrokers": [], "offerLots": 319, "offerFreq": 3, "offerBrokers": ["--"]}, {"price": 1790, "bidLots": 0, "bidFreq": 0, "bidBrokers": [], "offerLots": 53, "offerFreq": 2, "offerBrokers": ["--"]}, {"price": 1785, "bidLots": 0, "bidFreq": 0, "bidBrokers": [], "offerLots": 1060, "offerFreq": 1, "offerBrokers": ["--"]}, {"price": 1775, "bidLots": 0, "bidFreq": 0, "bidBrokers": [], "offerLots": 5, "offerFreq": 1, "offerBrokers": ["--"]}, {"price": 1760, "bidLots": 0, "bidFreq": 0, "bidBrokers": [], "offerLots": 8, "offerFreq": 2, "offerBrokers": ["--"]}, {"price": 1755, "bidLots": 0, "bidFreq": 0, "bidBrokers": [], "offerLots": 6, "offerFreq": 2, "offerBrokers": ["--"]}, {"price": 1750, "bidLots": 0, "bidFreq": 0, "bidBrokers": [], "offerLots": 44, "offerFreq": 5, "offerBrokers": ["--"]}, {"price": 1745, "bidLots": 0, "bidFreq": 0, "bidBrokers": [], "offerLots": 13, "offerFreq": 3, "offerBrokers": ["--"]}, {"price": 1740, "bidLots": 0, "bidFreq": 0, "bidBrokers": [], "offerLots": 144, "offerFreq": 4, "offerBrokers": ["--"]}, {"price": 1735, "bidLots": 0, "bidFreq": 0, "bidBrokers": [], "offerLots": 5, "offerFreq": 2, "offerBrokers": ["--"]}, {"price": 1730, "bidLots": 0, "bidFreq": 0, "bidBrokers": [], "offerLots": 1, "offerFreq": 1, "offerBrokers": ["--"]}, {"price": 1725, "bidLots": 0, "bidFreq": 0, "bidBrokers": [], "offerLots": 64, "offerFreq": 1, "offerBrokers": ["--"]}, {"price": 1720, "bidLots": 0, "bidFreq": 0, "bidBrokers": [], "offerLots": 169, "offerFreq": 4, "offerBrokers": ["--"]}, {"price": 1705, "bidLots": 0, "bidFreq": 0, "bidBrokers": [], "offerLots": 29, "offerFreq": 3, "offerBrokers": ["--"]}, {"price": 1700, "bidLots": 0, "bidFreq": 0, "bidBrokers": [], "offerLots": 1620, "offerFreq": 26, "offerBrokers": ["--"]}, {"price": 1695, "bidLots": 0, "bidFreq": 0, "bidBrokers": [], "offerLots": 207, "offerFreq": 13, "offerBrokers": ["--"]}, {"price": 1690, "bidLots": 0, "bidFreq": 0, "bidBrokers": [], "offerLots": 420, "offerFreq": 9, "offerBrokers": ["--"]}, {"price": 1685, "bidLots": 0, "bidFreq": 0, "bidBrokers": [], "offerLots": 705, "offerFreq": 6, "offerBrokers": ["--"]}, {"price": 1680, "bidLots": 0, "bidFreq": 0, "bidBrokers": [], "offerLots": 19, "offerFreq": 5, "offerBrokers": ["--"]}, {"price": 1675, "bidLots": 0, "bidFreq": 0, "bidBrokers": [], "offerLots": 125, "offerFreq": 7, "offerBrokers": ["--"]}, {"price": 1670, "bidLots": 0, "bidFreq": 0, "bidBrokers": [], "offerLots": 66, "offerFreq": 9, "offerBrokers": ["--"]}, {"price": 1665, "bidLots": 0, "bidFreq": 0, "bidBrokers": [], "offerLots": 507, "offerFreq": 4, "offerBrokers": ["--"]}, {"price": 1660, "bidLots": 0, "bidFreq": 0, "bidBrokers": [], "offerLots": 202, "offerFreq": 10, "offerBrokers": ["--"]}, {"price": 1655, "bidLots": 0, "bidFreq": 0, "bidBrokers": [], "offerLots": 209, "offerFreq": 14, "offerBrokers": ["--"]}, {"price": 1650, "bidLots": 0, "bidFreq": 0, "bidBrokers": [], "offerLots": 1043, "offerFreq": 41, "offerBrokers": ["--"]}, {"price": 1645, "bidLots": 0, "bidFreq": 0, "bidBrokers": [], "offerLots": 254, "offerFreq": 17, "offerBrokers": ["--"]}, {"price": 1640, "bidLots": 0, "bidFreq": 0, "bidBrokers": [], "offerLots": 299, "offerFreq": 21, "offerBrokers": ["--"]}, {"price": 1635, "bidLots": 0, "bidFreq": 0, "bidBrokers": [], "offerLots": 375, "offerFreq": 21, "offerBrokers": ["--"]}, {"price": 1630, "bidLots": 0, "bidFreq": 0, "bidBrokers": [], "offerLots": 460, "offerFreq": 23, "offerBrokers": ["--"]}, {"price": 1625, "bidLots": 0, "bidFreq": 0, "bidBrokers": [], "offerLots": 461, "offerFreq": 34, "offerBrokers": ["--"]}, {"price": 1620, "bidLots": 0, "bidFreq": 0, "bidBrokers": [], "offerLots": 1726, "offerFreq": 53, "offerBrokers": ["--"]}, {"price": 1615, "bidLots": 0, "bidFreq": 0, "bidBrokers": [], "offerLots": 2712, "offerFreq": 54, "offerBrokers": ["DR", "--"]}, {"price": 1610, "bidLots": 0, "bidFreq": 0, "bidBrokers": [], "offerLots": 741, "offerFreq": 29, "offerBrokers": ["--"]}, {"price": 1605, "bidLots": 0, "bidFreq": 0, "bidBrokers": [], "offerLots": 4996, "offerFreq": 27, "offerBrokers": ["--"]}, {"price": 1600, "bidLots": 0, "bidFreq": 0, "bidBrokers": [], "offerLots": 11869, "offerFreq": 59, "offerBrokers": ["XA", "--"]}, {"price": 1595, "bidLots": 7086, "bidFreq": 20, "bidBrokers": ["ZP", "KK", "XL", "--"], "offerLots": 0, "offerFreq": 0, "offerBrokers": []}, {"price": 1590, "bidLots": 16788, "bidFreq": 58, "bidBrokers": ["LG", "--"], "offerLots": 0, "offerFreq": 0, "offerBrokers": []}, {"price": 1585, "bidLots": 1665, "bidFreq": 72, "bidBrokers": ["--"], "offerLots": 0, "offerFreq": 0, "offerBrokers": []}, {"price": 1580, "bidLots": 2907, "bidFreq": 98, "bidBrokers": ["--"], "offerLots": 0, "offerFreq": 0, "offerBrokers": []}, {"price": 1575, "bidLots": 3845, "bidFreq": 143, "bidBrokers": ["--"], "offerLots": 0, "offerFreq": 0, "offerBrokers": []}, {"price": 1570, "bidLots": 2219, "bidFreq": 83, "bidBrokers": ["--"], "offerLots": 0, "offerFreq": 0, "offerBrokers": []}, {"price": 1565, "bidLots": 1105, "bidFreq": 41, "bidBrokers": ["--"], "offerLots": 0, "offerFreq": 0, "offerBrokers": []}, {"price": 1560, "bidLots": 3453, "bidFreq": 62, "bidBrokers": ["--"], "offerLots": 0, "offerFreq": 0, "offerBrokers": []}, {"price": 1555, "bidLots": 1039, "bidFreq": 31, "bidBrokers": ["--"], "offerLots": 0, "offerFreq": 0, "offerBrokers": []}, {"price": 1550, "bidLots": 4036, "bidFreq": 67, "bidBrokers": ["--"], "offerLots": 0, "offerFreq": 0, "offerBrokers": []}, {"price": 1545, "bidLots": 926, "bidFreq": 21, "bidBrokers": ["--"], "offerLots": 0, "offerFreq": 0, "offerBrokers": []}, {"price": 1540, "bidLots": 1363, "bidFreq": 33, "bidBrokers": ["--"], "offerLots": 0, "offerFreq": 0, "offerBrokers": []}, {"price": 1535, "bidLots": 1421, "bidFreq": 19, "bidBrokers": ["--"], "offerLots": 0, "offerFreq": 0, "offerBrokers": []}, {"price": 1530, "bidLots": 913, "bidFreq": 19, "bidBrokers": ["--"], "offerLots": 0, "offerFreq": 0, "offerBrokers": []}, {"price": 1525, "bidLots": 1864, "bidFreq": 25, "bidBrokers": ["--"], "offerLots": 0, "offerFreq": 0, "offerBrokers": []}, {"price": 1520, "bidLots": 539, "bidFreq": 19, "bidBrokers": ["--"], "offerLots": 0, "offerFreq": 0, "offerBrokers": []}, {"price": 1515, "bidLots": 76, "bidFreq": 9, "bidBrokers": ["--"], "offerLots": 0, "offerFreq": 0, "offerBrokers": []}, {"price": 1510, "bidLots": 474, "bidFreq": 13, "bidBrokers": ["--"], "offerLots": 0, "offerFreq": 0, "offerBrokers": []}, {"price": 1505, "bidLots": 1504, "bidFreq": 16, "bidBrokers": ["--"], "offerLots": 0, "offerFreq": 0, "offerBrokers": []}, {"price": 1500, "bidLots": 1149, "bidFreq": 60, "bidBrokers": ["--"], "offerLots": 0, "offerFreq": 0, "offerBrokers": []}, {"price": 1495, "bidLots": 770, "bidFreq": 3, "bidBrokers": ["--"], "offerLots": 0, "offerFreq": 0, "offerBrokers": []}, {"price": 1490, "bidLots": 134, "bidFreq": 11, "bidBrokers": ["--"], "offerLots": 0, "offerFreq": 0, "offerBrokers": []}, {"price": 1485, "bidLots": 187, "bidFreq": 5, "bidBrokers": ["--"], "offerLots": 0, "offerFreq": 0, "offerBrokers": []}, {"price": 1480, "bidLots": 133, "bidFreq": 6, "bidBrokers": ["--"], "offerLots": 0, "offerFreq": 0, "offerBrokers": []}, {"price": 1475, "bidLots": 6, "bidFreq": 3, "bidBrokers": ["--"], "offerLots": 0, "offerFreq": 0, "offerBrokers": []}, {"price": 1470, "bidLots": 44, "bidFreq": 4, "bidBrokers": ["--"], "offerLots": 0, "offerFreq": 0, "offerBrokers": []}, {"price": 1465, "bidLots": 10, "bidFreq": 4, "bidBrokers": ["--"], "offerLots": 0, "offerFreq": 0, "offerBrokers": []}, {"price": 1460, "bidLots": 99, "bidFreq": 5, "bidBrokers": ["--"], "offerLots": 0, "offerFreq": 0, "offerBrokers": []}, {"price": 1455, "bidLots": 70, "bidFreq": 3, "bidBrokers": ["--"], "offerLots": 0, "offerFreq": 0, "offerBrokers": []}, {"price": 1450, "bidLots": 545, "bidFreq": 26, "bidBrokers": ["--"], "offerLots": 0, "offerFreq": 0, "offerBrokers": []}, {"price": 1445, "bidLots": 293, "bidFreq": 4, "bidBrokers": ["--"], "offerLots": 0, "offerFreq": 0, "offerBrokers": []}, {"price": 1440, "bidLots": 44, "bidFreq": 5, "bidBrokers": ["--"], "offerLots": 0, "offerFreq": 0, "offerBrokers": []}, {"price": 1435, "bidLots": 143, "bidFreq": 2, "bidBrokers": ["--"], "offerLots": 0, "offerFreq": 0, "offerBrokers": []}, {"price": 1430, "bidLots": 133, "bidFreq": 6, "bidBrokers": ["--"], "offerLots": 0, "offerFreq": 0, "offerBrokers": []}, {"price": 1425, "bidLots": 92, "bidFreq": 3, "bidBrokers": ["--"], "offerLots": 0, "offerFreq": 0, "offerBrokers": []}, {"price": 1420, "bidLots": 2825, "bidFreq": 5, "bidBrokers": ["--"], "offerLots": 0, "offerFreq": 0, "offerBrokers": []}, {"price": 1415, "bidLots": 3, "bidFreq": 1, "bidBrokers": ["--"], "offerLots": 0, "offerFreq": 0, "offerBrokers": []}, {"price": 1410, "bidLots": 66, "bidFreq": 5, "bidBrokers": ["--"], "offerLots": 0, "offerFreq": 0, "offerBrokers": []}, {"price": 1405, "bidLots": 81, "bidFreq": 5, "bidBrokers": ["--"], "offerLots": 0, "offerFreq": 0, "offerBrokers": []}, {"price": 1400, "bidLots": 3411, "bidFreq": 23, "bidBrokers": ["--"], "offerLots": 0, "offerFreq": 0, "offerBrokers": []}, {"price": 1395, "bidLots": 6, "bidFreq": 2, "bidBrokers": ["--"], "offerLots": 0, "offerFreq": 0, "offerBrokers": []}, {"price": 1390, "bidLots": 34, "bidFreq": 3, "bidBrokers": ["--"], "offerLots": 0, "offerFreq": 0, "offerBrokers": []}, {"price": 1385, "bidLots": 232, "bidFreq": 2, "bidBrokers": ["--"], "offerLots": 0, "offerFreq": 0, "offerBrokers": []}, {"price": 1380, "bidLots": 128, "bidFreq": 3, "bidBrokers": ["--"], "offerLots": 0, "offerFreq": 0, "offerBrokers": []}, {"price": 1375, "bidLots": 8, "bidFreq": 5, "bidBrokers": ["--"], "offerLots": 0, "offerFreq": 0, "offerBrokers": []}, {"price": 1370, "bidLots": 87, "bidFreq": 3, "bidBrokers": ["--"], "offerLots": 0, "offerFreq": 0, "offerBrokers": []}, {"price": 1365, "bidLots": 1, "bidFreq": 1, "bidBrokers": ["--"], "offerLots": 0, "offerFreq": 0, "offerBrokers": []}, {"price": 1360, "bidLots": 224, "bidFreq": 2, "bidBrokers": ["--"], "offerLots": 0, "offerFreq": 0, "offerBrokers": []}, {"price": 1355, "bidLots": 20, "bidFreq": 3, "bidBrokers": ["--"], "offerLots": 0, "offerFreq": 0, "offerBrokers": []}, {"price": 1350, "bidLots": 397, "bidFreq": 22, "bidBrokers": ["--"], "offerLots": 0, "offerFreq": 0, "offerBrokers": []}, {"price": 1345, "bidLots": 4, "bidFreq": 2, "bidBrokers": ["--"], "offerLots": 0, "offerFreq": 0, "offerBrokers": []}, {"price": 1340, "bidLots": 100, "bidFreq": 7, "bidBrokers": ["--"], "offerLots": 0, "offerFreq": 0, "offerBrokers": []}]